Workbook
Name AssetM: [1]Table!$J$3:$K$13
Name Benjamin: OFFSET('[2]Weight Watch'!$B$9,'[2]Weight Watch'!$I$3-9,2,'[2]Weight Watch'!$I$2,1)
Name Client: [1]X!$C$9
Name DateF: OFFSET('[2]Weight Watch'!$B$9,'[2]Weight Watch'!$I$3-9,0,'[2]Weight Watch'!$I$2,1)
Name DefaultB: [1]X!$F$5
Name Difference: OFFSET([3]Salman!$G$9,0,0,[3]Salman!$B$4,1)
Name Eric: OFFSET('[2]Weight Watch'!$B$9,'[2]Weight Watch'!$I$3-9,4,'[2]Weight Watch'!$I$2,1)
Name FanF: OFFSET('[2]Weight Watch'!$B$9,'[2]Weight Watch'!$I$3-9,3,'[2]Weight Watch'!$I$2,1)
Name Footer: [1]X!$C$10
Name George: OFFSET('[2]Weight Watch'!$B$9,'[2]Weight Watch'!$I$3-9,3,'[2]Weight Watch'!$I$2,1)
Name Graham_Rates: OFFSET(Rate!$C$3,COUNT(Rates),0,-6,1)
Name Graham_Years: OFFSET(Rate!$C$3,COUNT(Rates),-1,-6,1)
Name LiF: OFFSET('[2]Weight Watch'!$B$9,'[2]Weight Watch'!$I$3-9,2,'[2]Weight Watch'!$I$2,1)
Name MeasDate: OFFSET('[2]Weight Watch'!$B$9,'[2]Weight Watch'!$I$3-9,0,'[2]Weight Watch'!$I$2,1)
Name MetMRV: [4]Table!$C$21:$D$31
Name QxTable: Qx!$B$4:$C$119
Name Rate: OFFSET([5]Rate!$C$4,0,0,COUNT([5]Rate!$C:$C))
Name Rates: Rate!$C$4:$C$24
Name Version: [1]X!$A$2
Name WangF: OFFSET('[2]Weight Watch'!$B$9,'[2]Weight Watch'!$I$3-9,4,'[2]Weight Watch'!$I$2,1)
Name Year: OFFSET([5]Rate!$B$4,0,0,COUNT([5]Rate!$B:$B))
Name Year158: '[6]FAS 158 Input'!$H$4
Name Years: Rate!$B$4:$B$24

Sheet Record
B2: Valuation Date | G2: 43466
B4: Employee Database
B5: ID | C5: Name | D5: Salary | E5: PY Salary | F5: Date of Birth | G5: Date of Hire | H5: Age | I5: Service
B6: 50001 | C6: Klendshoj,Roxanne | D6: 110000 | E6: 101000 | F6: 26363 | G6: 33665 | H6: =YEAR($G$2)-YEAR(F6)-IF($G$2<DATE(YEAR($G$2), MONTH(F6),DAY(F6)),1,0) -> 46 | I6: =ROUND((YEAR($G$2)-YEAR(G6))+(MONTH($G$2)-MONTH(G6))/12+(DAY($G$2)-DAY(G6))/365.25,0) -> 27
B7: 50002 | C7: Woodley,Jeanne M | D7: 99000 | E7: 91000 | F7: 19785 | G7: 42616 | H7: =YEAR($G$2)-YEAR(F7)-IF($G$2<DATE(YEAR($G$2), MONTH(F7),DAY(F7)),1,0) -> 64 | I7: =ROUND((YEAR($G$2)-YEAR(G7))+(MONTH($G$2)-MONTH(G7))/12+(DAY($G$2)-DAY(G7))/365.25,0) -> 2
B8: 50003 | C8: Bartho,Jerome Fion | D8: 98000 | E8: 90000 | F8: 20584 | G8: 37989 | H8: =YEAR($G$2)-YEAR(F8)-IF($G$2<DATE(YEAR($G$2), MONTH(F8),DAY(F8)),1,0) -> 62 | I8: =ROUND((YEAR($G$2)-YEAR(G8))+(MONTH($G$2)-MONTH(G8))/12+(DAY($G$2)-DAY(G8))/365.25,0) -> 15
B9: 50004 | C9: Benson,Scott G | D9: 97000 | E9: 89000 | F9: 20341 | G9: 40825 | H9: =YEAR($G$2)-YEAR(F9)-IF($G$2<DATE(YEAR($G$2), MONTH(F9),DAY(F9)),1,0) -> 63 | I9: =ROUND((YEAR($G$2)-YEAR(G9))+(MONTH($G$2)-MONTH(G9))/12+(DAY($G$2)-DAY(G9))/365.25,0) -> 7
B10: 50005 | C10: Aho,Diane | D10: 96000 | E10: 88000 | F10: 26458 | G10: 40973 | H10: =YEAR($G$2)-YEAR(F10)-IF($G$2<DATE(YEAR($G$2), MONTH(F10),DAY(F10)),1,0) -> 46 | I10: =ROUND((YEAR($G$2)-YEAR(G10))+(MONTH($G$2)-MONTH(G10))/12+(DAY($G$2)-DAY(G10))/365.25,0) -> 7
B11: 50006 | C11: Larson,DeeAnn Smith | D11: 95000 | E11: 87000 | F11: 23072 | G11: 36163 | H11: =YEAR($G$2)-YEAR(F11)-IF($G$2<DATE(YEAR($G$2), MONTH(F11),DAY(F11)),1,0) -> 55 | I11: =ROUND((YEAR($G$2)-YEAR(G11))+(MONTH($G$2)-MONTH(G11))/12+(DAY($G$2)-DAY(G11))/365.25,0) -> 20
B12: 50007 | C12: Nelson,Susann | D12: 100000 | E12: 92000 | F12: 20070 | G12: 32743 | H12: =YEAR($G$2)-YEAR(F12)-IF($G$2<DATE(YEAR($G$2), MONTH(F12),DAY(F12)),1,0) -> 64 | I12: =ROUND((YEAR($G$2)-YEAR(G12))+(MONTH($G$2)-MONTH(G12))/12+(DAY($G$2)-DAY(G12))/365.25,0) -> 29
B13: 50008 | C13: Asche,Tracy A | D13: 93000 | E13: 85000 | F13: 21491 | G13: 43078 | H13: =YEAR($G$2)-YEAR(F13)-IF($G$2<DATE(YEAR($G$2), MONTH(F13),DAY(F13)),1,0) -> 60 | I13: =ROUND((YEAR($G$2)-YEAR(G13))+(MONTH($G$2)-MONTH(G13))/12+(DAY($G$2)-DAY(G13))/365.25,0) -> 1
B14: 50009 | C14: Carlson,Robert Lee | D14: 92000 | E14: 84000 | F14: 20694 | G14: 36767 | H14: =YEAR($G$2)-YEAR(F14)-IF($G$2<DATE(YEAR($G$2), MONTH(F14),DAY(F14)),1,0) -> 62 | I14: =ROUND((YEAR($G$2)-YEAR(G14))+(MONTH($G$2)-MONTH(G14))/12+(DAY($G$2)-DAY(G14))/365.25,0) -> 18
B15: 50010 | C15: Donovan,Richard | D15: 91000 | E15: 83000 | F15: 22901 | G15: 32546 | H15: =YEAR($G$2)-YEAR(F15)-IF($G$2<DATE(YEAR($G$2), MONTH(F15),DAY(F15)),1,0) -> 56 | I15: =ROUND((YEAR($G$2)-YEAR(G15))+(MONTH($G$2)-MONTH(G15))/12+(DAY($G$2)-DAY(G15))/365.25,0) -> 30

Sheet Qx
B2: Mortality Table
B3: Age | C3: qx
B4: 5 | C4: 0.000237
B5: =B4+1 -> 6 | C5: 0.000227
B6: =B5+1 -> 7 | C6: 0.000217
B7: =B6+1 -> 8 | C7: 0.000201
B8: =B7+1 -> 9 | C8: 0.000194
B9: =B8+1 -> 10 | C9: 0.000197
B10: =B9+1 -> 11 | C10: 0.000208
B11: =B10+1 -> 12 | C11: 0.000226
B12: =B11+1 -> 13 | C12: 0.000255
B13: =B12+1 -> 14 | C13: 0.000297
B14: =B13+1 -> 15 | C14: 0.000345
B15: =B14+1 -> 16 | C15: 0.000391
B16: =B15+1 -> 17 | C16: 0.00043
... B119: =B118+1 -> 120 | C119: 1

Sheet Pivot Table
A1: Age by Service Table with total Salaries plus total PY Salaries
C3: Service
A4: Age | B4: Values | C4: 0-5 | D4: 6-10 | E4: 11-20 | F4: 20+ | G4: Grand Total
A5: 45-49 | B5: Sum of Total Salary | C5: 0 | D5: 184000 | E5: 0 | F5: 211000 | G5: 395000
B6: Count of Service | D6: 1 | F6: 1 | G6: 2
A7: 55-59 | B7: Sum of Total Salary | C7: 0 | D7: 0 | E7: 182000 | F7: 174000 | G7: 356000
B8: Count of Service | E8: 1 | F8: 1 | G8: 2
A9: 60-64 | B9: Sum of Total Salary | C9: 368000 | D9: 186000 | E9: 364000 | F9: 192000 | G9: 1110000
B10: Count of Service | C10: 2 | D10: 1 | E10: 2 | F10: 1 | G10: 6

Sheet Annuity
B2: Life Annuity
B3: Current Age | H3: =Statement!E12 -> 46
B4: Annual Payment | H4: =Statement!E16 -> 4540.8
B5: Interest Rate | H5: =VLOOKUP(H7,Rate!B4:C24,2,FALSE) -> 0.04
B7: Contract Year | H7: =Rate!B28 -> 2019
B8: Annuity Factor | H8: =SUM(H13:H121) -> 18.683689
B9: Annuity Value | H9: =H8*H4 -> 84838.894
B11: Excel Calculation
B12: Age | C12: Qx | D12: px | E12: tpx | H12: Discount Value
B13: =IF(H3="",65,H3) -> 46 | C13: =IF(B13="","",VLOOKUP(B13,QxTable,2)) -> 0.001722 | D13: =IF(B13="","",1-C13) -> 0.998278 | E13: 1 | H13: =IF(B13="","",E13/(1+$H$5)^(B13-$B$13)) -> 1
B14: =IF(B13>=120,"",B13+1) -> 47 | C14: =IF(B14="","",VLOOKUP(B14,QxTable,2)) -> 0.001899 | D14: =IF(B14="","",1-C14) -> 0.998101 | E14: =IF(B14="","",E13*D13) -> 0.998278 | H14: =IF(B14="","",E14/(1+$H$5)^(B14-$B$13)) -> 0.95988269
B15: =IF(B14>=120,"",B14+1) -> 48 | C15: =IF(B15="","",VLOOKUP(B15,QxTable,2)) -> 0.002102 | D15: =IF(B15="","",1-C15) -> 0.997898 | E15: =IF(B15="","",E14*D14) -> 0.99638227 | H15: =IF(B15="","",E15/(1+$H$5)^(B15-$B$13)) -> 0.92121142
B16: =IF(B15>=120,"",B15+1) -> 49 | C16: =IF(B16="","",VLOOKUP(B16,QxTable,2)) -> 0.002326 | D16: =IF(B16="","",1-C16) -> 0.997674 | E16: =IF(B16="","",E15*D15) -> 0.99428787 | H16: =IF(B16="","",E16/(1+$H$5)^(B16-$B$13)) -> 0.8839183
B17: =IF(B16>=120,"",B16+1) -> 50 | C17: =IF(B17="","",VLOOKUP(B17,QxTable,2)) -> 0.002579 | D17: =IF(B17="","",1-C17) -> 0.997421 | E17: =IF(B17="","",E16*D16) -> 0.99197516 | H17: =IF(B17="","",E17/(1+$H$5)^(B17-$B$13)) -> 0.84794452
B18: =IF(B17>=120,"",B17+1) -> 51 | C18: =IF(B18="","",VLOOKUP(B18,QxTable,2)) -> 0.002872 | D18: =IF(B18="","",1-C18) -> 0.997128 | E18: =IF(B18="","",E17*D17) -> 0.98941686 | H18: =IF(B18="","",E18/(1+$H$5)^(B18-$B$13)) -> 0.81322853
B19: =IF(B18>=120,"",B18+1) -> 52 | C19: =IF(B19="","",VLOOKUP(B19,QxTable,2)) -> 0.003213 | D19: =IF(B19="","",1-C19) -> 0.996787 | E19: =IF(B19="","",E18*D18) -> 0.98657525 | H19: =IF(B19="","",E19/(1+$H$5)^(B19-$B$13)) -> 0.77970475
B20: =IF(B19>=120,"",B19+1) -> 53 | C20: =IF(B20="","",VLOOKUP(B20,QxTable,2)) -> 0.003584 | D20: =IF(B20="","",1-C20) -> 0.996416 | E20: =IF(B20="","",E19*D19) -> 0.98340539 | H20: =IF(B20="","",E20/(1+$H$5)^(B20-$B$13)) -> 0.74730727
B21: =IF(B20>=120,"",B20+1) -> 54 | C21: =IF(B21="","",VLOOKUP(B21,QxTable,2)) -> 0.003979 | D21: =IF(B21="","",1-C21) -> 0.996021 | E21: =IF(B21="","",E20*D20) -> 0.97988086 | H21: =IF(B21="","",E21/(1+$H$5)^(B21-$B$13)) -> 0.71598935
B22: =IF(B21>=120,"",B21+1) -> 55 | C22: =IF(B22="","",VLOOKUP(B22,QxTable,2)) -> 0.004425 | D22: =IF(B22="","",1-C22) -> 0.995575 | E22: =IF(B22="","",E21*D21) -> 0.97598191 | H22: =IF(B22="","",E22/(1+$H$5)^(B22-$B$13)) -> 0.68571195
B23: =IF(B22>=120,"",B22+1) -> 56 | C23: =IF(B23="","",VLOOKUP(B23,QxTable,2)) -> 0.004949 | D23: =IF(B23="","",1-C23) -> 0.995051 | E23: =IF(B23="","",E22*D22) -> 0.97166319 | H23: =IF(B23="","",E23/(1+$H$5)^(B23-$B$13)) -> 0.65642084
B24: =IF(B23>=120,"",B23+1) -> 57 | C24: =IF(B24="","",VLOOKUP(B24,QxTable,2)) -> 0.005581 | D24: =IF(B24="","",1-C24) -> 0.994419 | E24: =IF(B24="","",E23*D23) -> 0.96685443 | H24: =IF(B24="","",E24/(1+$H$5)^(B24-$B$13)) -> 0.6280502
B25: =IF(B24>=120,"",B24+1) -> 58 | C25: =IF(B25="","",VLOOKUP(B25,QxTable,2)) -> 0.0063 | D25: =IF(B25="","",1-C25) -> 0.9937 | E25: =IF(B25="","",E24*D24) -> 0.96145842 | H25: =IF(B25="","",E25/(1+$H$5)^(B25-$B$13)) -> 0.60052409
... B87: =IF(B86>=120,"",B86+1) -> 120 | C87: =IF(B87="","",VLOOKUP(B87,QxTable,2)) -> 1 | D87: =IF(B87="","",1-C87) -> 0 | E87: =IF(B87="","",E86*D86) -> 9.679251e-08 | H87: =IF(B87="","",E87/(1+$H$5)^(B87-$B$13)) -> 5.3134261e-09
B88: =IF(B87>=120,"",B87+1) | C88: =IF(B88="","",VLOOKUP(B88,QxTable,2)) | D88: =IF(B88="","",1-C88) | H88: =IF(B88="","",E88/(1+$H$5)^(B88-$B$13))
B89: =IF(B88>=120,"",B88+1) | C89: =IF(B89="","",VLOOKUP(B89,QxTable,2)) | D89: =IF(B89="","",1-C89) | E89: =IF(B89="","",E88*D88) | H89: =IF(B89="","",E89/(1+$H$5)^(B89-$B$13))
B90: =IF(B89>=120,"",B89+1) | C90: =IF(B90="","",VLOOKUP(B90,QxTable,2)) | D90: =IF(B90="","",1-C90) | E90: =IF(B90="","",E89*D89) | H90: =IF(B90="","",E90/(1+$H$5)^(B90-$B$13))
B91: =IF(B90>=120,"",B90+1) | C91: =IF(B91="","",VLOOKUP(B91,QxTable,2)) | D91: =IF(B91="","",1-C91) | E91: =IF(B91="","",E90*D90) | H91: =IF(B91="","",E91/(1+$H$5)^(B91-$B$13))
B92: =IF(B91>=120,"",B91+1) | C92: =IF(B92="","",VLOOKUP(B92,QxTable,2)) | D92: =IF(B92="","",1-C92) | E92: =IF(B92="","",E91*D91) | H92: =IF(B92="","",E92/(1+$H$5)^(B92-$B$13))
B93: =IF(B92>=120,"",B92+1) | C93: =IF(B93="","",VLOOKUP(B93,QxTable,2)) | D93: =IF(B93="","",1-C93) | E93: =IF(B93="","",E92*D92) | H93: =IF(B93="","",E93/(1+$H$5)^(B93-$B$13))
B94: =IF(B93>=120,"",B93+1) | C94: =IF(B94="","",VLOOKUP(B94,QxTable,2)) | D94: =IF(B94="","",1-C94) | E94: =IF(B94="","",E93*D93) | H94: =IF(B94="","",E94/(1+$H$5)^(B94-$B$13))
B95: =IF(B94>=120,"",B94+1) | C95: =IF(B95="","",VLOOKUP(B95,QxTable,2)) | D95: =IF(B95="","",1-C95) | E95: =IF(B95="","",E94*D94) | H95: =IF(B95="","",E95/(1+$H$5)^(B95-$B$13))
B96: =IF(B95>=120,"",B95+1) | C96: =IF(B96="","",VLOOKUP(B96,QxTable,2)) | D96: =IF(B96="","",1-C96) | E96: =IF(B96="","",E95*D95) | H96: =IF(B96="","",E96/(1+$H$5)^(B96-$B$13))
B97: =IF(B96>=120,"",B96+1) | C97: =IF(B97="","",VLOOKUP(B97,QxTable,2)) | D97: =IF(B97="","",1-C97) | E97: =IF(B97="","",E96*D96) | H97: =IF(B97="","",E97/(1+$H$5)^(B97-$B$13))
B98: =IF(B97>=120,"",B97+1) | C98: =IF(B98="","",VLOOKUP(B98,QxTable,2)) | D98: =IF(B98="","",1-C98) | E98: =IF(B98="","",E97*D97) | H98: =IF(B98="","",E98/(1+$H$5)^(B98-$B$13))
B99: =IF(B98>=120,"",B98+1) | C99: =IF(B99="","",VLOOKUP(B99,QxTable,2)) | D99: =IF(B99="","",1-C99) | E99: =IF(B99="","",E98*D98) | H99: =IF(B99="","",E99/(1+$H$5)^(B99-$B$13))
B100: =IF(B99>=120,"",B99+1) | C100: =IF(B100="","",VLOOKUP(B100,QxTable,2)) | D100: =IF(B100="","",1-C100) | E100: =IF(B100="","",E99*D99) | H100: =IF(B100="","",E100/(1+$H$5)^(B100-$B$13))
... B113: =IF(B112>=120,"",B112+1) | C113: =IF(B113="","",VLOOKUP(B113,QxTable,2)) | D113: =IF(B113="","",1-C113) | E113: =IF(B113="","",E112*D112) | H113: =IF(B113="","",E113/(1+$H$5)^(B113-$B$13))

Sheet Rate
B2: Interest Rate | D2: The rate in a year is used to calculate annuity value for the contracts made in that year.
B3: Year | C3: Rate
B4: 2012 | C4: 0.04
B5: 2013 | C5: 0.075
B6: 2014 | C6: 0.065
B7: 2015 | C7: 0.0725
B8: 2016 | C8: 0.065
B9: 2017 | C9: 0.04
B10: 2018 | C10: 0.045
B11: 2019 | C11: 0.04 | D11: For example, if a plan is terminated in 2019 and the annuity contract is purchased in the same year, then the rate of 4.00% is used to determine the annuity value
B12: 2020
B13: 2021
B14: 2022
B15: 2023
B16: 2024
B17: 2025
B18: 2026
B19: 2027
B20: 2028
B21: 2029
B22: 2030
B23: 2031
B24: 2032
B26: Current Year Info
B27: Contract Year | C27: Rate
B28: 2019 | C28: =IF(VLOOKUP(B28,B4:C24,2,FALSE)="","",VLOOKUP(B28,B4:C24,2,FALSE)) -> 0.04

Sheet Statement
C3: Benefit Statement
C5: Name | E5: =RIGHT(Calc!B3,LEN(Calc!B3)-SEARCH(",",Calc!B3))&" "&LEFT(Calc!B3,SEARCH(",",Calc!B3)-1) -> Diane Aho
C7: Date of Birth | E7: =VLOOKUP($E$26,Record!$B$6:$I$15,5,FALSE) -> 26458
C8: Date of Hire | E8: =VLOOKUP($E$26,Record!$B$6:$I$15,6,FALSE) -> 40973
C9: Date of Participation | E9: =IF(MONTH(Calc!B9)=1,Calc!B9, IF(MONTH(Calc!B9)<=7,DATE(YEAR(Calc!B9),7,1),DATE(YEAR(Calc!B9)+1,1,1))) -> 41456
C10: Date of Normal Retirement | E10: =EOMONTH((MAX(EDATE(E9,60),EDATE(E7,12*65)))-1,0)+1 -> 50222
C11: Salary | E11: =VLOOKUP($E$26,Record!$B$6:$I$15,3,FALSE) -> 96000
C12: Age last birthday | E12: =VLOOKUP($E$26,Record!$B$6:$I$15,7,FALSE) -> 46
C13: Service since the participation date | E13: =(YEAR(Record!$G$2)-YEAR(E9))+(MONTH(Record!$G$2)-MONTH(E9))/12+IF(DAY(Record!$G$2)<DAY(E9),-1/12,0) -> 5.5
C14: Annual Benefit | E14: =2%*E11*E13 -> 10560
C15: Early Retirement factor | E15: =MAX(0,1-0.03*(YEAR(E10)-YEAR(Record!$G$2)+IF(MONTH(E10)>MONTH(Record!$G$2),1,0))) -> 0.43
C16: Early Retirement Benefit | E16: =E14*E15 -> 4540.8
C17: Annuity purchase value | E17: =Annuity!H9 -> 84838.894
C19: Retirement Goal | E19: =E11*10 -> 960000
C20: Achieved Goal Percentage | E20: =E17/E19 -> 0.088373848
C23: ="This statement is prepared on "&TEXT(WORKDAY(DATE(Rate!B28,5,1)-1,8),"mmm d, yyyy") -> This statement is prepared on May 10, 2019
C26: Identification Number --- input item | E26: 50005

Sheet Calc
B2: Name
B3: =VLOOKUP(Statement!$E$26,Record!$B$6:$I$15,2,FALSE) -> Aho,Diane
B5: One Year Anniversary of Employement
B6: =EDATE(Statement!E8,12) -> 41338
B8: First day of the month after B6
B9: =EOMONTH(B6-1,0)+1 -> 41365

Sheet Sort DB
B2: Valuation Date | G2: 43466
B4: Employee Database
B5: ID | C5: Name | D5: Salary | E5: PY Salary | F5: Date of Birth | G5: Date of Hire | H5: Age | I5: Service
B6: 50007 | C6: Nelson,Susann | D6: 100000 | E6: 92000 | F6: 20070 | G6: 32743 | H6: =YEAR($G$2)-YEAR(F6)-IF($G$2<DATE(YEAR($G$2), MONTH(F6),DAY(F6)),1,0) -> 64 | I6: =ROUND((YEAR($G$2)-YEAR(G6))+(MONTH($G$2)-MONTH(G6))/12+(DAY($G$2)-DAY(G6))/365.25,0) -> 29
B7: 50002 | C7: Woodley,Jeanne M | D7: 99000 | E7: 91000 | F7: 19785 | G7: 42616 | H7: =YEAR($G$2)-YEAR(F7)-IF($G$2<DATE(YEAR($G$2), MONTH(F7),DAY(F7)),1,0) -> 64 | I7: =ROUND((YEAR($G$2)-YEAR(G7))+(MONTH($G$2)-MONTH(G7))/12+(DAY($G$2)-DAY(G7))/365.25,0) -> 2
B8: 50004 | C8: Benson,Scott G | D8: 97000 | E8: 89000 | F8: 20341 | G8: 40825 | H8: =YEAR($G$2)-YEAR(F8)-IF($G$2<DATE(YEAR($G$2), MONTH(F8),DAY(F8)),1,0) -> 63 | I8: =ROUND((YEAR($G$2)-YEAR(G8))+(MONTH($G$2)-MONTH(G8))/12+(DAY($G$2)-DAY(G8))/365.25,0) -> 7
B9: 50003 | C9: Bartho,Jerome Fion | D9: 98000 | E9: 90000 | F9: 20584 | G9: 37989 | H9: =YEAR($G$2)-YEAR(F9)-IF($G$2<DATE(YEAR($G$2), MONTH(F9),DAY(F9)),1,0) -> 62 | I9: =ROUND((YEAR($G$2)-YEAR(G9))+(MONTH($G$2)-MONTH(G9))/12+(DAY($G$2)-DAY(G9))/365.25,0) -> 15
B10: 50009 | C10: Carlson,Robert Lee | D10: 92000 | E10: 84000 | F10: 20694 | G10: 36767 | H10: =YEAR($G$2)-YEAR(F10)-IF($G$2<DATE(YEAR($G$2), MONTH(F10),DAY(F10)),1,0) -> 62 | I10: =ROUND((YEAR($G$2)-YEAR(G10))+(MONTH($G$2)-MONTH(G10))/12+(DAY($G$2)-DAY(G10))/365.25,0) -> 18
B11: 50008 | C11: Asche,Tracy A | D11: 93000 | E11: 85000 | F11: 21491 | G11: 43078 | H11: =YEAR($G$2)-YEAR(F11)-IF($G$2<DATE(YEAR($G$2), MONTH(F11),DAY(F11)),1,0) -> 60 | I11: =ROUND((YEAR($G$2)-YEAR(G11))+(MONTH($G$2)-MONTH(G11))/12+(DAY($G$2)-DAY(G11))/365.25,0) -> 1
B12: 50010 | C12: Donovan,Richard | D12: 91000 | E12: 83000 | F12: 22901 | G12: 32546 | H12: =YEAR($G$2)-YEAR(F12)-IF($G$2<DATE(YEAR($G$2), MONTH(F12),DAY(F12)),1,0) -> 56 | I12: =ROUND((YEAR($G$2)-YEAR(G12))+(MONTH($G$2)-MONTH(G12))/12+(DAY($G$2)-DAY(G12))/365.25,0) -> 30
B13: 50006 | C13: Larson,DeeAnn Smith | D13: 95000 | E13: 87000 | F13: 23072 | G13: 36163 | H13: =YEAR($G$2)-YEAR(F13)-IF($G$2<DATE(YEAR($G$2), MONTH(F13),DAY(F13)),1,0) -> 55 | I13: =ROUND((YEAR($G$2)-YEAR(G13))+(MONTH($G$2)-MONTH(G13))/12+(DAY($G$2)-DAY(G13))/365.25,0) -> 20
B14: 50005 | C14: Aho,Diane | D14: 96000 | E14: 88000 | F14: 26458 | G14: 40973 | H14: =YEAR($G$2)-YEAR(F14)-IF($G$2<DATE(YEAR($G$2), MONTH(F14),DAY(F14)),1,0) -> 46 | I14: =ROUND((YEAR($G$2)-YEAR(G14))+(MONTH($G$2)-MONTH(G14))/12+(DAY($G$2)-DAY(G14))/365.25,0) -> 7
B15: 50001 | C15: Klendshoj,Roxanne | D15: 110000 | E15: 101000 | F15: 26363 | G15: 33665 | H15: =YEAR($G$2)-YEAR(F15)-IF($G$2<DATE(YEAR($G$2), MONTH(F15),DAY(F15)),1,0) -> 46 | I15: =ROUND((YEAR($G$2)-YEAR(G15))+(MONTH($G$2)-MONTH(G15))/12+(DAY($G$2)-DAY(G15))/365.25,0) -> 27

Sheet Filter DB
D2: Summary Info:
D3: Number of Records | E3: =SUBTOTAL(2,B10:B19) -> 10 | F3: Maximum Age | G3: =SUBTOTAL(4,H10:H19) -> 64
D4: Total Salary of Current Year | E4: =SUBTOTAL(9,D10:D19) -> 971000 | F4: Minimum Age | G4: =SUBTOTAL(5,H10:H19) -> 46
D5: Average Salary of Current Year | E5: =SUBTOTAL(1,D10:D19) -> 97100 | F5: Average Service | G5: =SUBTOTAL(1,I10:I19) -> 15.6
B6: Valuation Date | I6: 43466
B8: Employee Database
B9: ID | C9: Name | D9: Salary | E9: PY Salary | F9: Date of Birth | G9: Date of Hire | H9: Age | I9: Service
B10: 50001 | C10: Klendshoj,Roxanne | D10: 110000 | E10: 101000 | F10: 26363 | G10: 33665 | H10: =YEAR($I$6)-YEAR(F10)-IF($I$6<DATE(YEAR($I$6), MONTH(F10),DAY(F10)),1,0) -> 46 | I10: =ROUND((YEAR($I$6)-YEAR(G10))+(MONTH($I$6)-MONTH(G10))/12+(DAY($I$6)-DAY(G10))/365.25,0) -> 27
B11: 50002 | C11: Woodley,Jeanne M | D11: 99000 | E11: 91000 | F11: 19785 | G11: 42616 | H11: =YEAR($I$6)-YEAR(F11)-IF($I$6<DATE(YEAR($I$6), MONTH(F11),DAY(F11)),1,0) -> 64 | I11: =ROUND((YEAR($I$6)-YEAR(G11))+(MONTH($I$6)-MONTH(G11))/12+(DAY($I$6)-DAY(G11))/365.25,0) -> 2
B12: 50003 | C12: Bartho,Jerome Fion | D12: 98000 | E12: 90000 | F12: 20584 | G12: 37989 | H12: =YEAR($I$6)-YEAR(F12)-IF($I$6<DATE(YEAR($I$6), MONTH(F12),DAY(F12)),1,0) -> 62 | I12: =ROUND((YEAR($I$6)-YEAR(G12))+(MONTH($I$6)-MONTH(G12))/12+(DAY($I$6)-DAY(G12))/365.25,0) -> 15
B13: 50004 | C13: Benson,Scott G | D13: 97000 | E13: 89000 | F13: 20341 | G13: 40825 | H13: =YEAR($I$6)-YEAR(F13)-IF($I$6<DATE(YEAR($I$6), MONTH(F13),DAY(F13)),1,0) -> 63 | I13: =ROUND((YEAR($I$6)-YEAR(G13))+(MONTH($I$6)-MONTH(G13))/12+(DAY($I$6)-DAY(G13))/365.25,0) -> 7
B14: 50005 | C14: Aho,Diane | D14: 96000 | E14: 88000 | F14: 26458 | G14: 40973 | H14: =YEAR($I$6)-YEAR(F14)-IF($I$6<DATE(YEAR($I$6), MONTH(F14),DAY(F14)),1,0) -> 46 | I14: =ROUND((YEAR($I$6)-YEAR(G14))+(MONTH($I$6)-MONTH(G14))/12+(DAY($I$6)-DAY(G14))/365.25,0) -> 7
B15: 50006 | C15: Larson,DeeAnn Smith | D15: 95000 | E15: 87000 | F15: 23072 | G15: 36163 | H15: =YEAR($I$6)-YEAR(F15)-IF($I$6<DATE(YEAR($I$6), MONTH(F15),DAY(F15)),1,0) -> 55 | I15: =ROUND((YEAR($I$6)-YEAR(G15))+(MONTH($I$6)-MONTH(G15))/12+(DAY($I$6)-DAY(G15))/365.25,0) -> 20
B16: 50007 | C16: Nelson,Susann | D16: 100000 | E16: 92000 | F16: 20070 | G16: 32743 | H16: =YEAR($I$6)-YEAR(F16)-IF($I$6<DATE(YEAR($I$6), MONTH(F16),DAY(F16)),1,0) -> 64 | I16: =ROUND((YEAR($I$6)-YEAR(G16))+(MONTH($I$6)-MONTH(G16))/12+(DAY($I$6)-DAY(G16))/365.25,0) -> 29
B17: 50008 | C17: Asche,Tracy A | D17: 93000 | E17: 85000 | F17: 21491 | G17: 43078 | H17: =YEAR($I$6)-YEAR(F17)-IF($I$6<DATE(YEAR($I$6), MONTH(F17),DAY(F17)),1,0) -> 60 | I17: =ROUND((YEAR($I$6)-YEAR(G17))+(MONTH($I$6)-MONTH(G17))/12+(DAY($I$6)-DAY(G17))/365.25,0) -> 1
B18: 50009 | C18: Carlson,Robert Lee | D18: 92000 | E18: 84000 | F18: 20694 | G18: 36767 | H18: =YEAR($I$6)-YEAR(F18)-IF($I$6<DATE(YEAR($I$6), MONTH(F18),DAY(F18)),1,0) -> 62 | I18: =ROUND((YEAR($I$6)-YEAR(G18))+(MONTH($I$6)-MONTH(G18))/12+(DAY($I$6)-DAY(G18))/365.25,0) -> 18
B19: 50010 | C19: Donovan,Richard | D19: 91000 | E19: 83000 | F19: 22901 | G19: 32546 | H19: =YEAR($I$6)-YEAR(F19)-IF($I$6<DATE(YEAR($I$6), MONTH(F19),DAY(F19)),1,0) -> 56 | I19: =ROUND((YEAR($I$6)-YEAR(G19))+(MONTH($I$6)-MONTH(G19))/12+(DAY($I$6)-DAY(G19))/365.25,0) -> 30

Sheet Filter Advance
D2: Age | E2: Salary
D3: >50 | E3: >80000
B4: Valuation Date | D4: <40 | E4: >80000 | G4: 43466
B6: Employee Database
B7: ID | C7: Name | D7: Salary | E7: PY Salary | F7: Date of Birth | G7: Date of Hire | H7: Age | I7: Service
B8: 50001 | C8: Klendshoj,Roxanne | D8: 110000 | E8: 101000 | F8: 26363 | G8: 33665 | H8: =YEAR($G$4)-YEAR(F8)-IF($G$4<DATE(YEAR($G$4), MONTH(F8),DAY(F8)),1,0) -> 46 | I8: =ROUND((YEAR($G$4)-YEAR(G8))+(MONTH($G$4)-MONTH(G8))/12+(DAY($G$4)-DAY(G8))/365.25,0) -> 27
B9: 50002 | C9: Woodley,Jeanne M | D9: 99000 | E9: 91000 | F9: 19785 | G9: 42616 | H9: =YEAR($G$4)-YEAR(F9)-IF($G$4<DATE(YEAR($G$4), MONTH(F9),DAY(F9)),1,0) -> 64 | I9: =ROUND((YEAR($G$4)-YEAR(G9))+(MONTH($G$4)-MONTH(G9))/12+(DAY($G$4)-DAY(G9))/365.25,0) -> 2
B10: 50003 | C10: Bartho,Jerome Fion | D10: 98000 | E10: 90000 | F10: 20584 | G10: 37989 | H10: =YEAR($G$4)-YEAR(F10)-IF($G$4<DATE(YEAR($G$4), MONTH(F10),DAY(F10)),1,0) -> 62 | I10: =ROUND((YEAR($G$4)-YEAR(G10))+(MONTH($G$4)-MONTH(G10))/12+(DAY($G$4)-DAY(G10))/365.25,0) -> 15
B11: 50004 | C11: Benson,Scott G | D11: 97000 | E11: 89000 | F11: 20341 | G11: 40825 | H11: =YEAR($G$4)-YEAR(F11)-IF($G$4<DATE(YEAR($G$4), MONTH(F11),DAY(F11)),1,0) -> 63 | I11: =ROUND((YEAR($G$4)-YEAR(G11))+(MONTH($G$4)-MONTH(G11))/12+(DAY($G$4)-DAY(G11))/365.25,0) -> 7
B12: 50005 | C12: Aho,Diane | D12: 96000 | E12: 88000 | F12: 26458 | G12: 40973 | H12: =YEAR($G$4)-YEAR(F12)-IF($G$4<DATE(YEAR($G$4), MONTH(F12),DAY(F12)),1,0) -> 46 | I12: =ROUND((YEAR($G$4)-YEAR(G12))+(MONTH($G$4)-MONTH(G12))/12+(DAY($G$4)-DAY(G12))/365.25,0) -> 7
B13: 50006 | C13: Larson,DeeAnn Smith | D13: 95000 | E13: 87000 | F13: 23072 | G13: 36163 | H13: =YEAR($G$4)-YEAR(F13)-IF($G$4<DATE(YEAR($G$4), MONTH(F13),DAY(F13)),1,0) -> 55 | I13: =ROUND((YEAR($G$4)-YEAR(G13))+(MONTH($G$4)-MONTH(G13))/12+(DAY($G$4)-DAY(G13))/365.25,0) -> 20
B14: 50007 | C14: Nelson,Susann | D14: 100000 | E14: 92000 | F14: 20070 | G14: 32743 | H14: =YEAR($G$4)-YEAR(F14)-IF($G$4<DATE(YEAR($G$4), MONTH(F14),DAY(F14)),1,0) -> 64 | I14: =ROUND((YEAR($G$4)-YEAR(G14))+(MONTH($G$4)-MONTH(G14))/12+(DAY($G$4)-DAY(G14))/365.25,0) -> 29
B15: 50008 | C15: Asche,Tracy A | D15: 93000 | E15: 85000 | F15: 21491 | G15: 43078 | H15: =YEAR($G$4)-YEAR(F15)-IF($G$4<DATE(YEAR($G$4), MONTH(F15),DAY(F15)),1,0) -> 60 | I15: =ROUND((YEAR($G$4)-YEAR(G15))+(MONTH($G$4)-MONTH(G15))/12+(DAY($G$4)-DAY(G15))/365.25,0) -> 1
B16: 50009 | C16: Carlson,Robert Lee | D16: 92000 | E16: 84000 | F16: 20694 | G16: 36767 | H16: =YEAR($G$4)-YEAR(F16)-IF($G$4<DATE(YEAR($G$4), MONTH(F16),DAY(F16)),1,0) -> 62 | I16: =ROUND((YEAR($G$4)-YEAR(G16))+(MONTH($G$4)-MONTH(G16))/12+(DAY($G$4)-DAY(G16))/365.25,0) -> 18
B17: 50010 | C17: Donovan,Richard | D17: 91000 | E17: 83000 | F17: 22901 | G17: 32546 | H17: =YEAR($G$4)-YEAR(F17)-IF($G$4<DATE(YEAR($G$4), MONTH(F17),DAY(F17)),1,0) -> 56 | I17: =ROUND((YEAR($G$4)-YEAR(G17))+(MONTH($G$4)-MONTH(G17))/12+(DAY($G$4)-DAY(G17))/365.25,0) -> 30
